odoo/addons/account_payment_paired_internal_transfer/README.rst
odoo/addons/account_payment_paired_internal_transfer/__init__.py
odoo/addons/account_payment_paired_internal_transfer/__manifest__.py
odoo/addons/account_payment_paired_internal_transfer/i18n/account_payment_paired_internal_transfer.pot
odoo/addons/account_payment_paired_internal_transfer/i18n/pt_BR.po
odoo/addons/account_payment_paired_internal_transfer/models/__init__.py
odoo/addons/account_payment_paired_internal_transfer/models/account_payment.py
odoo/addons/account_payment_paired_internal_transfer/readme/CONFIGURE.rst
odoo/addons/account_payment_paired_internal_transfer/readme/CONTRIBUTORS.rst
odoo/addons/account_payment_paired_internal_transfer/readme/DESCRIPTION.rst
odoo/addons/account_payment_paired_internal_transfer/readme/USAGE.rst
odoo/addons/account_payment_paired_internal_transfer/static/description/icon.png
odoo/addons/account_payment_paired_internal_transfer/static/description/index.html
odoo/addons/account_payment_paired_internal_transfer/views/account_payment_views.xml
odoo14_addon_account_payment_paired_internal_transfer-14.0.1.0.1.dist-info/METADATA
odoo14_addon_account_payment_paired_internal_transfer-14.0.1.0.1.dist-info/WHEEL
odoo14_addon_account_payment_paired_internal_transfer-14.0.1.0.1.dist-info/top_level.txt
odoo14_addon_account_payment_paired_internal_transfer-14.0.1.0.1.dist-info/RECORD
